thomas_linden/__init__.py
thomas_linden/__main__.py
thomas_linden/names.txt
thomas_linden/speaker.py
thomas_linden/speakers/__init__.py
thomas_linden/speakers/thomas.py
thomas_linden-0.3.0.dist-info/licenses/LICENSE.txt
thomas_linden-0.3.0.dist-info/METADATA
thomas_linden-0.3.0.dist-info/WHEEL
thomas_linden-0.3.0.dist-info/entry_points.txt
thomas_linden-0.3.0.dist-info/top_level.txt
thomas_linden-0.3.0.dist-info/RECORD
