Metadata-Version: 2.4
Name: thomas_linden
Version: 0.3.0
Summary: My first package!
Author-email: Thomas Linden <thomaz.linden@gmail.com>
Maintainer-email: Thomas Linden <thomaz.linden@gmail.com>
License-Expression: BSD-3-Clause
Keywords: sandbox
Requires-Python: >=3.9
License-File: LICENSE.txt
Requires-Dist: colorama~=0.0
Provides-Extra: dev
Requires-Dist: twine; extra == "dev"
Requires-Dist: build; extra == "dev"
Dynamic: license-file
